hangman_game/__init__.py
hangman_game/board.py
hangman_game/cli.py
hangman_game/game.py
eldar_hangman-1.0.0.dist-info/METADATA
eldar_hangman-1.0.0.dist-info/WHEEL
eldar_hangman-1.0.0.dist-info/entry_points.txt
eldar_hangman-1.0.0.dist-info/top_level.txt
eldar_hangman-1.0.0.dist-info/RECORD
