Metadata-Version: 2.4
Name: eldar-hangman
Version: 1.0.0
Summary: Classic Hangman game with CLI and colors
Author: Eldar
Requires-Python: >=3.8
Requires-Dist: colorama
